scieco/__init__.py
scieco/bigleaf.py
scieco/evapotranspiration.py
scieco/photosynthesis.py
scieco/respiration.py
scieco-0.0.1.dist-info/METADATA
scieco-0.0.1.dist-info/WHEEL
scieco-0.0.1.dist-info/top_level.txt
scieco-0.0.1.dist-info/RECORD
