Metadata-Version: 2.1
Name: scieco
Version: 0.0.1
Summary: Ecology
Home-page: https://github.com/soonyenju/scieco
Author: Songyan Zhu
Author-email: zhusy93@gmail.com
License: MIT Licence
Keywords: Geosciences,geospatial,data science
Platform: any
